README
env.sh
run
setup.cfg
setup.py
adminish_categories.egg-info/PKG-INFO
adminish_categories.egg-info/SOURCES.txt
adminish_categories.egg-info/dependency_links.txt
adminish_categories.egg-info/entry_points.txt
adminish_categories.egg-info/not-zip-safe
adminish_categories.egg-info/top_level.txt
adminishcategories/__init__.py
categories/__init__.py
categories.egg-info/PKG-INFO
categories.egg-info/SOURCES.txt
categories.egg-info/dependency_links.txt
categories.egg-info/entry_points.txt
categories.egg-info/not-zip-safe
categories.egg-info/top_level.txt
categories/tests/test_categorish.py