Metadata-Version: 1.0
Name: adminish-categories
Version: 0.1.1dev
Summary: support library for adminish
Home-page: http://ish.io
Author: Tim Parkin & Matt Goodall
Author-email: info@timparkin.co.uk
License: UNKNOWN
Platform: UNKNOWN
